Twinnppt/__init__.py
Twinnppt/ppt.py
Twinnppt-0.0.4.dist-info/LICENSE
Twinnppt-0.0.4.dist-info/METADATA
Twinnppt-0.0.4.dist-info/WHEEL
Twinnppt-0.0.4.dist-info/top_level.txt
Twinnppt-0.0.4.dist-info/RECORD
