Metadata-Version: 2.1
Name: Twinnppt
Version: 0.0.4
Summary: ppt package
Author-email: twinn <saurabh.kumar@tooli.qa>
Classifier: Programming Language :: Python :: 3
Classifier: License :: OSI Approved :: MIT License
Classifier: Operating System :: OS Independent
Requires-Python: >=3.8
License-File: LICENSE
